meow_ai/__init__.py
meow_ai-1.0.3.dist-info/METADATA
meow_ai-1.0.3.dist-info/WHEEL
meow_ai-1.0.3.dist-info/entry_points.txt
meow_ai-1.0.3.dist-info/RECORD
