Metadata-Version: 2.1
Name: meow-ai
Version: 1.0.3
Summary: 以 OpenAI API 格式使用 LLM
Author: meowjiao321
Author-email: meowjiao321@163.com
Requires-Python: >=3.8,<4.0
Classifier: Programming Language :: Python :: 3
Classifier: Programming Language :: Python :: 3.8
Classifier: Programming Language :: Python :: 3.9
Classifier: Programming Language :: Python :: 3.10
Classifier: Programming Language :: Python :: 3.11
Classifier: Programming Language :: Python :: 3.12
Requires-Dist: colorama (>=0.4.6,<0.5.0)
Requires-Dist: openai (>=1.3.6,<2.0.0)
Requires-Dist: pyreadline3 (>=3.4.1,<4.0.0)
